Metadata-Version: 2.4
Name: latex-generator-dazaii
Version: 0.1.0
Summary: LaTeX generator for tables and images
Author: Arseni Voikin
License: MIT
Project-URL: Homepage, https://github.com/voikin/mhs-python-hw
Requires-Python: >=3.8
